Metadata-Version: 1.1
Name: wav-loopy
Version: 0.1.1
Summary: A simple WAV audio file looper: read file -> write file looped by X
Home-page: https://github.com/gilzoide/wav-loopy
Author: gilzoide
Author-email: gilzoide@gmail.com
License: GPLv3
Keywords: audio wav loop
Platform: UNKNOWN
Classifier: Development Status :: 3 - Alpha
Classifier: Environment :: Console
Classifier: Programming Language :: Python :: 2
Classifier: Programming Language :: Python :: 3
